pytest_intercept_remote/__init__.py
pytest_intercept_remote/_version.py
pytest_intercept_remote/fixtures.py
pytest_intercept_remote/intercept_helpers.py
pytest_intercept_remote/plugin.py
pytest_intercept_remote/remote_status.py
pytest_intercept_remote-1.25.dist-info/LICENSE
pytest_intercept_remote-1.25.dist-info/METADATA
pytest_intercept_remote-1.25.dist-info/WHEEL
pytest_intercept_remote-1.25.dist-info/entry_points.txt
pytest_intercept_remote-1.25.dist-info/top_level.txt
pytest_intercept_remote-1.25.dist-info/RECORD
