Metadata-Version: 2.1
Name: pytest-intercept-remote
Version: 1.25
Summary: Pytest plugin for intercepting outgoing connection requests during pytest run.
Home-page: https://github.com/devanshshukla99/pytest-intercept-remote
Author: devanshshukla99
Author-email: devanshshukla99@outlook.com
License: BSD
Platform: UNKNOWN
Classifier: Development Status :: 4 - Beta
Classifier: Framework :: Pytest
Classifier: Intended Audience :: Developers
Classifier: License :: OSI Approved :: BSD License
Classifier: Operating System :: OS Independent
Classifier: Programming Language :: Python
Classifier: Programming Language :: Python :: 3
Classifier: Programming Language :: Python :: 3 :: Only
Classifier: Programming Language :: Python :: 3.7
Classifier: Programming Language :: Python :: 3.8
Classifier: Programming Language :: Python :: 3.9
Classifier: Topic :: Software Development :: Testing
Classifier: Topic :: Utilities
Requires-Python: >=3.6
Requires-Dist: pytest (>=4.6)
Requires-Dist: requests (>=2.25.1)
